wx_sdk/__init__.py
wx_sdk/wx_sdk.py
wx_sdk-1.0.5.dist-info/DESCRIPTION.rst
wx_sdk-1.0.5.dist-info/METADATA
wx_sdk-1.0.5.dist-info/RECORD
wx_sdk-1.0.5.dist-info/WHEEL
wx_sdk-1.0.5.dist-info/metadata.json
wx_sdk-1.0.5.dist-info/top_level.txt
